atomic_dict/__init__.py
atomic_dict/capi/doc.h
atomic_dict/capi/init.c
atomic_dict/capi/methods.c
atomic_dict/capi/methods.h
atomic_dict/capi/types.h
atomic_dict/capi.cpython-314-x86_64-linux-gnu.so
atomic_dict/capi.pyi
atomic_dict/core.py
atomic_dict/py.typed
atomic_dict-0.5.0.dist-info/LICENSE
atomic_dict-0.5.0.dist-info/METADATA
atomic_dict-0.5.0.dist-info/WHEEL
atomic_dict-0.5.0.dist-info/RECORD
