Metadata-Version: 2.3
Name: atomic_dict
Version: 0.5.0
Summary: A library for lock-free shared 64-bit dictionaries
License: BSD-3
Author: Wesley W. Terpstra
Author-email: wesley@sifive.com
Requires-Python: >=3.10,<4.0
Classifier: License :: Other/Proprietary License
Classifier: Programming Language :: Python :: 3
Classifier: Programming Language :: Python :: 3.10
Classifier: Programming Language :: Python :: 3.11
Classifier: Programming Language :: Python :: 3.12
Classifier: Programming Language :: Python :: 3.13
Project-URL: Repository, https://github.com/terpstra/atomic-dict
